ozkr/__init__.py
ozkr-0.1.0.dist-info/WHEEL
ozkr-0.1.0.dist-info/METADATA
ozkr-0.1.0.dist-info/RECORD
