Metadata-Version: 2.1
Name: ozkr
Version: 0.1.0
Summary: 
Author: quaxsze
Author-email: plum.stanislas@gmail.com
Requires-Python: >=3.9,<4.0
Classifier: Programming Language :: Python :: 3
Classifier: Programming Language :: Python :: 3.10
Classifier: Programming Language :: Python :: 3.9
Requires-Dist: pendulum (>=2.1.2,<3.0.0)
